Workbook

Sheet Assumptions & Drivers
B1: IntelliPrivart
B2: NEXTUTE EDTECH - CASE B: THE DATA MOAT
B3: Base Model Assumptions & Macro Drivers (Finance Club, IIT Patna Case 2026)
B5: 1. Coaching Institute Baseline Profile
B7: Average Student Count per Institute | C7: 400 | D7: Students | E7: Range: 150 to 2,000 students
B8: Annual Tuition Fee per Student | C8: 60000 | D8: INR / Year | E8: Range: ₹30,000 to ₹1,50,000
B9: Academic Billing Months per Year | C9: 10 | D9: Months | E9: April - January core active test cycle
B10: Average Monthly Fee per Student | C10: =C8/C9 -> 6000 | D10: INR / Month | E10: Calculated over active months
B11: Annual Mid-session Dropout Rate | C11: 0.12 | D11: % of Batch | E11: Industry baseline: 8% to 15%
B12: Average Dropout Timing (Month of Session) | C12: 4 | D12: Month | E12: Dropouts peak between Month 3 and 5
B13: Uncollected Fees Lost per Dropped Student | C13: =C10*(C9-C12) -> 36000 | D13: INR / Student | E13: Remaining 6 months unpaid installments
B14: 2. SaaS Pricing & Packaging (Nextute Intelligence)
B16: Tier 1: Essentials (Up to 150 Students) | C16: 5999 | D16: INR / Month | E16: Fixed flat subscription
B17: Tier 2: Intelligence Base Fee (Includes 300 Students) | C17: 9999 | D17: INR / Month | E17: Primary target tier
B18: Tier 2: Additional Student Variable Fee | C18: 30 | D18: INR / Student/Month | E18: Per student above 300
B19: Tier 2: Blended Monthly Fee for 400 Students | C19: =C17+(400-300)*C18 -> 12999 | D19: INR / Month | E19: Base + 100 * ₹30
B20: Tier 3: Enterprise Rate (>600 Students) | C20: 28 | D20: INR / Student / Month | E20: Custom volume pricing
B21: 3. Direct Service & Technology COGS (Per Student/Month)
B23: AWS / Multi-tenant Cloud Infrastructure | C23: 2 | D23: INR / Student / Month | E23: PostgreSQL + compute hosting
B24: GenAI Inference (LLM Student/Parent Reports) | C24: 2.5 | D24: INR / Student / Month | E24: Batch quantized models + RAG
B25: WhatsApp Business Cloud API Messaging | C25: 4 | D25: INR / Student / Month | E25: ~8 notifications/reports @ ₹0.50
B26: OMR Vision / OCR Processing | C26: 0.5 | D26: INR / Student / Month | E26: Serverless image processing pipeline
B27: Total Technology COGS per Student / Month | C27: =SUM(C23:C26) -> 9 | D27: INR / Student / Month | E27: True marginal tech cost
B28: 4. Sales, Marketing & Onboarding Assumptions
B30: Field Sales CAC per Institute | C30: 24000 | D30: INR / Institute | E30: Field visits in Patna, Kota, Lucknow
B31: Onboarding & Teacher Training Cost | C31: 6000 | D31: INR / Institute | E31: Data migration & OCR onboarding
B32: Total Customer Acquisition & Setup Cost | C32: =C30+C31 -> 30000 | D32: INR / Institute | E32: All-in CAC per acquired institute
B33: Average Sales Cycle Duration | C33: 4 | D33: Weeks | E33: Peak window: March - June admissions
B34: Annual Institute Logo Churn Rate | C34: 0.12 | D34: % / Year | E34: Equivalent to ~1.0% blended monthly churn
B35: Monthly Effective Logo Churn | C35: =1-(1-C34)^(1/12) -> 0.010596241 | D35: % / Month | E35: Compounded monthly attrition

Sheet Institute ROI Calculator
B2: COACHING INSTITUTE ROI CALCULATOR
B3: Demonstrating Measurable Financial Payback for Institute Directors
B5: Parameter / Metric | C5: Value | D5: Unit | E5: Methodology / Rationale
B6: Baseline Student Enrollment | C6: ='Assumptions & Drivers'!C7 -> 400 | D6: Students | E6: Standard mid-sized test-prep institute
B7: Annual Fee per Student | C7: ='Assumptions & Drivers'!C8 -> 60000 | D7: INR | E7: Average fees across 10-month curriculum
B8: Total Annual Tuition Billed | C8: =C6*C7 -> 24000000 | D8: INR | E8: Gross revenue potential of institute
B9: Historical Dropout Rate | C9: ='Assumptions & Drivers'!C11 -> 0.12 | D9: % | E9: Students leaving before session completion
B10: Number of Dropped Students | C10: =C6*C9 -> 48 | D10: Students | E10: Total students lost per academic cycle
B11: Uncollected Fees Lost per Dropout | C11: ='Assumptions & Drivers'!C13 -> 36000 | D11: INR | E11: Remaining 6 months unpaid installments
B12: Total Annual Fee Leakage | C12: =C10*C11 -> 1728000 | D12: INR | E12: Total cash lost to student attrition
B13: Nextute Early-Warning Intervention Impact
B15: Expected Dropout Prevention Efficiency | C15: 0.15 | D15: % Saved | E15: Targeted remedial & mentor alerts save 15%
B16: Students Retained via Early Warning | C16: =ROUND(C10*C15, 0) -> 7 | D16: Students | E16: Net students kept in institute
B17: Direct Fee Revenue Recovered | C17: =C16*C11 -> 252000 | D17: INR | E17: Recovered uncollected tuition fees
B18: Annual Nextute Platform Cost | C18: ='Assumptions & Drivers'!C19*'Assumptions & Drivers'!C9 -> 129990 | D18: INR | E18: 10 months active Tier 2 billing
B19: Net Profit Gain for Coaching Owner | C19: =C17-C18 -> 122010 | D19: INR | E19: Direct bottom-line profit expansion
B20: Institute ROI Multiple | C20: =C17/C18 -> 1.9386107 | D20: Multiple | E20: Fee Saved divided by Platform Cost
B21: Breakeven Threshold (Students to Save) | C21: =C18/C11 -> 3.6108333 | D21: Students | E21: Students needed to save to reach 1.0x ROI

Sheet Platform Unit Economics
B2: NEXTUTE PLATFORM UNIT ECONOMICS (PER INSTITUTE)
B3: Deconstructing CAC, Marginal COGS, Payback, and Lifetime Value
B5: Unit Metric | C5: Value / Formula | D5: Unit | E5: Benchmark / Comment
B6: Monthly Revenue per Institute (MRPA) | C6: ='Assumptions & Drivers'!C19 -> 12999 | D6: INR | E6: Tier 2 hybrid plan for 400 students
B7: Direct Technology COGS | C7: ='Assumptions & Drivers'!C27*'Assumptions & Drivers'!C7 -> 3600 | D7: INR | E7: Cloud, GenAI, and WhatsApp Cloud API
B8: Customer Success & Support Allocation | C8: 1800 | D8: INR | E8: 1 dedicated support rep per 25 institutes
B9: Total Monthly Cost to Serve | C9: =C7+C8 -> 5400 | D9: INR | E9: Variable + allocated direct support
B10: Monthly Contribution Margin (Gross Profit) | C10: =C6-C9 -> 7599 | D10: INR | E10: Operating gross profit generated
B11: Gross Margin % | C11: =C10/C6 -> 0.58458343 | D11: % | E11: Healthy B2B vertical SaaS gross margin
B12: Acquisition Efficiency & Payback
B14: Field Sales & Demo CAC | C14: ='Assumptions & Drivers'!C30 -> 24000 | D14: INR | E14: Tier 2 city direct sales acquisition cost
B15: Institute Setup & Onboarding | C15: ='Assumptions & Drivers'!C31 -> 6000 | D15: INR | E15: Data migration & staff training
B16: Total Customer Acquisition Cost (CAC) | C16: =C14+C15 -> 30000 | D16: INR | E16: All-in cost to activate new institute
B17: CAC Payback Period | C17: =C16/C10 -> 3.9478879 | D17: Months | E17: Recoupment time from contribution margin
B18: Lifetime Value & Retention (LTV)
B20: Annual Logo Churn Rate | C20: ='Assumptions & Drivers'!C34 -> 0.12 | D20: % | E20: Observed annual institute churn
B21: Expected Institute Lifespan (Years) | C21: =1/C20 -> 8.3333333 | D21: Years | E21: 1 / Annual Churn Rate
B22: Expected Institute Lifespan (Months) | C22: =C21*12 -> 100 | D22: Months | E22: Months active on Nextute
B23: Active Billing Months per Lifespan | C23: =C21*'Assumptions & Drivers'!C9 -> 83.333333 | D23: Months | E23: Excludes summer vacation dormant periods
B24: Customer Lifetime Value (LTV) | C24: =C23*C10 -> 633250 | D24: INR | E24: Cumulative contribution margin over life
B25: LTV : CAC Ratio | C25: =C24/C16 -> 21.108333 | D25: Multiple | E25: Golden standard SaaS benchmark: >= 3.0x

Sheet 3-Year Projections
B2: NEXTUTE EDTECH - 3-YEAR P&L & CASH FLOW PROJECTION
B3: Demonstrating Path to Profitability & Capital Efficiency (in INR Lakhs)
B5: P&L Line Item (₹ Lakhs) | C5: Year 1 (Q1) | D5: Year 1 (Q2) | E5: Year 1 (Q3) | F5: Year 1 (Q4) | G5: Year 1 Total | H5: Year 2 Total | I5: Year 3 Total
B6: Active Institutes (End of Period) | C6: 10 | D6: 20 | E6: 35 | F6: 50 | G6: =F6 -> 50 | H6: 180 | I6: 520
B7: Total Students on Platform | C7: 4000 | D7: 8000 | E7: 14000 | F7: 20000 | G7: =F7 -> 20000 | H7: 72000 | I7: 208000
B8: Revenue Streams
B10: Platform SaaS Subscription | C10: 3.9 | D10: 7.8 | E10: 13.65 | F10: 19.5 | G10: =SUM(C10:F10) -> 44.85 | H10: 187.2 | I10: 594.88
B11: Parent WhatsApp Report Add-on | C11: 0.6 | D11: 1.2 | E11: 2.1 | F11: 3 | G11: =SUM(C11:F11) -> 6.9 | H11: 32.4 | I11: 112.32
B12: Gross Revenue | C12: =C10+C11 -> 4.5 | D12: =D10+D11 -> 9 | E12: =E10+E11 -> 15.75 | F12: =F10+F11 -> 22.5 | G12: =SUM(G10:G11) -> 51.75 | H12: =H10+H11 -> 219.6 | I12: =I10+I11 -> 707.2
B13: Cost of Goods Sold (COGS)
B15: Cloud & Compute Infrastructure | C15: 0.24 | D15: 0.48 | E15: 0.84 | F15: 1.2 | G15: =SUM(C15:F15) -> 2.76 | H15: 12.96 | I15: 41.6
B16: GenAI Inference & Token Costs | C16: 0.3 | D16: 0.6 | E16: 1.05 | F16: 1.5 | G16: =SUM(C16:F16) -> 3.45 | H16: 16.2 | I16: 52
B17: WhatsApp Cloud API Delivery | C17: 0.48 | D17: 0.96 | E17: 1.68 | F17: 2.4 | G17: =SUM(C17:F17) -> 5.52 | H17: 25.92 | I17: 83.2
B18: Customer Support & Onboarding | C18: 0.54 | D18: 1.08 | E18: 1.89 | F18: 2.7 | G18: =SUM(C18:F18) -> 6.21 | H18: 23.33 | I18: 67.39
B19: Total COGS | C19: =SUM(C15:C18) -> 1.56 | D19: =SUM(D15:D18) -> 3.12 | E19: =SUM(E15:E18) -> 5.46 | F19: =SUM(F15:F18) -> 7.8 | G19: =SUM(G15:G18) -> 17.94 | H19: =SUM(H15:H18) -> 78.41 | I19: =SUM(I15:I18) -> 244.19
B20: Gross Profit | C20: =C12-C19 -> 2.94 | D20: =D12-D19 -> 5.88 | E20: =E12-E19 -> 10.29 | F20: =F12-F19 -> 14.7 | G20: =G12-G19 -> 33.81 | H20: =H12-H19 -> 141.19 | I20: =I12-I19 -> 463.01
B21: Gross Margin % | C21: =C20/C12 -> 0.65333333 | D21: =D20/D12 -> 0.65333333 | E21: =E20/E12 -> 0.65333333 | F21: =F20/F12 -> 0.65333333 | G21: =G20/G12 -> 0.65333333 | H21: =H20/H12 -> 0.64294171 | I21: =I20/I12 -> 0.65470871
B22: Operating Expenses (OPEX)
B24: Sales & Marketing (CAC Field Demos) | C24: 3 | D24: 3 | E24: 4.5 | F24: 4.5 | G24: =SUM(C24:F24) -> 15 | H24: 39 | I24: 102
B25: Engineering, ML & Product R&D | C25: 6 | D25: 6 | E25: 7.5 | F25: 7.5 | G25: =SUM(C25:F25) -> 27 | H25: 42 | I25: 78
B26: General & Administrative (G&A) | C26: 1.5 | D26: 1.5 | E26: 2 | F26: 2 | G26: =SUM(C26:F26) -> 7 | H26: 12 | I26: 24
B27: Total Operating Expenses | C27: =SUM(C24:C26) -> 10.5 | D27: =SUM(D24:D26) -> 10.5 | E27: =SUM(E24:E26) -> 14 | F27: =SUM(F24:F26) -> 14 | G27: =SUM(G24:G26) -> 49 | H27: =SUM(H24:H26) -> 93 | I27: =SUM(I24:I26) -> 204
B29: EBITDA | C29: =C20-C27 -> -7.56 | D29: =D20-D27 -> -4.62 | E29: =E20-E27 -> -3.71 | F29: =F20-F27 -> 0.7 | G29: =G20-G27 -> -15.19 | H29: =H20-H27 -> 48.19 | I29: =I20-I27 -> 259.01
B30: EBITDA Margin % | C30: =C29/C12 -> -1.68 | D30: =D29/D12 -> -0.51333333 | E30: =E29/E12 -> -0.23555556 | F30: =F29/F12 -> 0.031111111 | G30: =G29/G12 -> -0.29352657 | H30: =H29/H12 -> 0.21944444 | I30: =I29/I12 -> 0.36624717

Sheet Sensitivity Analysis
B2: TWO-WAY SENSITIVITY & SCENARIO ANALYSIS
B3: Stress-Testing Unit Economics and Institute Value Proposition Against Uncertainties
B5: Table 1: Institute ROI Multiple Sensitivity (Fee per Student vs. Dropout Prevention %)
B6: Annual Student Tuition Fee | D6: 40000 | E6: 50000 | F6: 60000 | G6: 75000 | H6: 90000
B7: 5% Dropout Reduction | C7: 0.05 | D7: =(400*0.12*(D$6/10*6)*$C7)/(400*35*10) -> 0.41142857 | E7: =(400*0.12*(E$6/10*6)*$C7)/(400*35*10) -> 0.51428571 | F7: =(400*0.12*(F$6/10*6)*$C7)/(400*35*10) -> 0.61714286 | G7: =(400*0.12*(G$6/10*6)*$C7)/(400*35*10) -> 0.77142857 | H7: =(400*0.12*(H$6/10*6)*$C7)/(400*35*10) -> 0.92571429
B8: 10% Dropout Reduction | C8: 0.1 | D8: =(400*0.12*(D$6/10*6)*$C8)/(400*35*10) -> 0.82285714 | E8: =(400*0.12*(E$6/10*6)*$C8)/(400*35*10) -> 1.0285714 | F8: =(400*0.12*(F$6/10*6)*$C8)/(400*35*10) -> 1.2342857 | G8: =(400*0.12*(G$6/10*6)*$C8)/(400*35*10) -> 1.5428571 | H8: =(400*0.12*(H$6/10*6)*$C8)/(400*35*10) -> 1.8514286
B9: 15% Dropout Reduction | C9: 0.15 | D9: =(400*0.12*(D$6/10*6)*$C9)/(400*35*10) -> 1.2342857 | E9: =(400*0.12*(E$6/10*6)*$C9)/(400*35*10) -> 1.5428571 | F9: =(400*0.12*(F$6/10*6)*$C9)/(400*35*10) -> 1.8514286 | G9: =(400*0.12*(G$6/10*6)*$C9)/(400*35*10) -> 2.3142857 | H9: =(400*0.12*(H$6/10*6)*$C9)/(400*35*10) -> 2.7771429
B10: 20% Dropout Reduction | C10: 0.2 | D10: =(400*0.12*(D$6/10*6)*$C10)/(400*35*10) -> 1.6457143 | E10: =(400*0.12*(E$6/10*6)*$C10)/(400*35*10) -> 2.0571429 | F10: =(400*0.12*(F$6/10*6)*$C10)/(400*35*10) -> 2.4685714 | G10: =(400*0.12*(G$6/10*6)*$C10)/(400*35*10) -> 3.0857143 | H10: =(400*0.12*(H$6/10*6)*$C10)/(400*35*10) -> 3.7028571
B11: 25% Dropout Reduction | C11: 0.25 | D11: =(400*0.12*(D$6/10*6)*$C11)/(400*35*10) -> 2.0571429 | E11: =(400*0.12*(E$6/10*6)*$C11)/(400*35*10) -> 2.5714286 | F11: =(400*0.12*(F$6/10*6)*$C11)/(400*35*10) -> 3.0857143 | G11: =(400*0.12*(G$6/10*6)*$C11)/(400*35*10) -> 3.8571429 | H11: =(400*0.12*(H$6/10*6)*$C11)/(400*35*10) -> 4.6285714
B13: Key Takeaway: Even at a conservative 10% dropout reduction for a ₹50,000 institute, ROI is 1.03x (breaks even).
B16: Table 2: Nextute LTV/CAC Ratio Sensitivity (Annual Churn vs. Blended CAC)
B17: Blended Acquisition Cost (CAC) | D17: 20000 | E17: 25000 | F17: 30000 | G17: 35000 | H17: 40000
B18: 8% Annual Churn | C18: 0.08 | D18: =((1/$C18)*10*'Platform Unit Economics'!C10)/D$17 -> 47.49375 | E18: =((1/$C18)*10*'Platform Unit Economics'!C10)/E$17 -> 37.995 | F18: =((1/$C18)*10*'Platform Unit Economics'!C10)/F$17 -> 31.6625 | G18: =((1/$C18)*10*'Platform Unit Economics'!C10)/G$17 -> 27.139286 | H18: =((1/$C18)*10*'Platform Unit Economics'!C10)/H$17 -> 23.746875
B19: 10% Annual Churn | C19: 0.1 | D19: =((1/$C19)*10*'Platform Unit Economics'!C10)/D$17 -> 37.995 | E19: =((1/$C19)*10*'Platform Unit Economics'!C10)/E$17 -> 30.396 | F19: =((1/$C19)*10*'Platform Unit Economics'!C10)/F$17 -> 25.33 | G19: =((1/$C19)*10*'Platform Unit Economics'!C10)/G$17 -> 21.711429 | H19: =((1/$C19)*10*'Platform Unit Economics'!C10)/H$17 -> 18.9975
B20: 12% Annual Churn | C20: 0.12 | D20: =((1/$C20)*10*'Platform Unit Economics'!C10)/D$17 -> 31.6625 | E20: =((1/$C20)*10*'Platform Unit Economics'!C10)/E$17 -> 25.33 | F20: =((1/$C20)*10*'Platform Unit Economics'!C10)/F$17 -> 21.108333 | G20: =((1/$C20)*10*'Platform Unit Economics'!C10)/G$17 -> 18.092857 | H20: =((1/$C20)*10*'Platform Unit Economics'!C10)/H$17 -> 15.83125
B21: 15% Annual Churn | C21: 0.15 | D21: =((1/$C21)*10*'Platform Unit Economics'!C10)/D$17 -> 25.33 | E21: =((1/$C21)*10*'Platform Unit Economics'!C10)/E$17 -> 20.264 | F21: =((1/$C21)*10*'Platform Unit Economics'!C10)/F$17 -> 16.886667 | G21: =((1/$C21)*10*'Platform Unit Economics'!C10)/G$17 -> 14.474286 | H21: =((1/$C21)*10*'Platform Unit Economics'!C10)/H$17 -> 12.665
B22: 20% Annual Churn | C22: 0.2 | D22: =((1/$C22)*10*'Platform Unit Economics'!C10)/D$17 -> 18.9975 | E22: =((1/$C22)*10*'Platform Unit Economics'!C10)/E$17 -> 15.198 | F22: =((1/$C22)*10*'Platform Unit Economics'!C10)/F$17 -> 12.665 | G22: =((1/$C22)*10*'Platform Unit Economics'!C10)/G$17 -> 10.855714 | H22: =((1/$C22)*10*'Platform Unit Economics'!C10)/H$17 -> 9.49875
B24: Key Takeaway: The business model maintains LTV/CAC > 3.0x across all realistic stress scenarios.
